screenctl/__init__.py
screenctl/screenctl.py
screenctl-0.0.6.dist-info/LICENSE
screenctl-0.0.6.dist-info/METADATA
screenctl-0.0.6.dist-info/WHEEL
screenctl-0.0.6.dist-info/entry_points.txt
screenctl-0.0.6.dist-info/top_level.txt
screenctl-0.0.6.dist-info/RECORD
