Metadata-Version: 2.1
Name: screenctl
Version: 0.0.6
Summary: screenctl 0.0.6, Controller for screen
Home-page: https://github.com/QGrain/screenctl
Author: Zhiyu Zhang
Author-email: zhiyuzhang999@gmail.com
License: Apache-2.0
Classifier: License :: OSI Approved :: Apache Software License
Classifier: Programming Language :: Python
Classifier: Programming Language :: Python :: 3
Classifier: Programming Language :: Python :: 3.8
License-File: LICENSE
